aisapi/__init__.py
aisapi/const.py
aisapi/ws.py
aisapi-0.1.1.dist-info/METADATA
aisapi-0.1.1.dist-info/RECORD
aisapi-0.1.1.dist-info/WHEEL
aisapi-0.1.1.dist-info/top_level.txt
