Metadata-Version: 2.1
Name: aisapi
Version: 0.1.1
Summary: UNKNOWN
Home-page: https://github.com/sviete/AIS-api
Author: AI-Speaker
Author-email: info@ai-speaker.com
License: UNKNOWN
Platform: UNKNOWN
Classifier: Programming Language :: Python :: 3
Classifier: License :: OSI Approved :: MIT License
Classifier: Operating System :: OS Independent
Requires-Dist: aiohttp
Requires-Dist: async-timeout
